odoo8_addon_l10n_nl_bsn-8.0.0.1.0.99.dev16-py2.7-nspkg.pth
odoo8_addon_l10n_nl_bsn-8.0.0.1.0.99.dev16.dist-info/METADATA
odoo8_addon_l10n_nl_bsn-8.0.0.1.0.99.dev16.dist-info/RECORD
odoo8_addon_l10n_nl_bsn-8.0.0.1.0.99.dev16.dist-info/WHEEL
odoo8_addon_l10n_nl_bsn-8.0.0.1.0.99.dev16.dist-info/namespace_packages.txt
odoo8_addon_l10n_nl_bsn-8.0.0.1.0.99.dev16.dist-info/top_level.txt
odoo_addons/l10n_nl_bsn/README.rst
odoo_addons/l10n_nl_bsn/__init__.py
odoo_addons/l10n_nl_bsn/__openerp__.py
odoo_addons/l10n_nl_bsn/i18n/l10n_nl_bsn.pot
odoo_addons/l10n_nl_bsn/i18n/nl.po
odoo_addons/l10n_nl_bsn/models/__init__.py
odoo_addons/l10n_nl_bsn/models/res_partner.py
odoo_addons/l10n_nl_bsn/static/description/icon.png
odoo_addons/l10n_nl_bsn/views/res_partner.xml
